mcp2py/__init__.py
mcp2py/client.py
mcp2py/elicitation.py
mcp2py/event_loop.py
mcp2py/exceptions.py
mcp2py/loader.py
mcp2py/registry.py
mcp2py/roots.py
mcp2py/sampling.py
mcp2py/schema.py
mcp2py/server.py
mcp2py/stubs.py
mcp2py-0.4.0.dist-info/METADATA
mcp2py-0.4.0.dist-info/WHEEL
mcp2py-0.4.0.dist-info/licenses/LICENSE
mcp2py-0.4.0.dist-info/RECORD
