Metadata-Version: 2.4
Name: mcp2py
Version: 0.4.0
Summary: Turn any MCP server into a Python module
Project-URL: Homepage, https://github.com/maximerivest/mcp2py
Project-URL: Documentation, https://github.com/maximerivest/mcp2py#readme
Project-URL: Repository, https://github.com/maximerivest/mcp2py
Project-URL: Issues, https://github.com/maximerivest/mcp2py/issues
Author-email: Maxime Rivest <mrive052@gmail.com>
License: MIT
License-File: LICENSE
Keywords: ai,llm,mcp,model-context-protocol,tools
Classifier: Development Status :: 3 - Alpha
Classifier: Intended Audience :: Developers
Classifier: License :: OSI Approved :: MIT License
Classifier: Programming Language :: Python :: 3
Classifier: Programming Language :: Python :: 3.13
Requires-Python: >=3.11
Requires-Dist: litellm>=1.0.0
Requires-Dist: mcp>=1.18.0
Provides-Extra: dev
Requires-Dist: mypy>=1.8.0; extra == 'dev'
Requires-Dist: pytest-asyncio>=0.23.0; extra == 'dev'
Requires-Dist: pytest-cov>=4.1.0; extra == 'dev'
Requires-Dist: pytest>=8.0.0; extra == 'dev'
